lendres/__init__.py
lendres/algorithms/PoissonDiskSampling.py
lendres/algorithms/Search.py
lendres/algorithms/__init__.py
lendres/computervision/ImageDataHelper.py
lendres/computervision/ImageHelper.py
lendres/computervision/__init__.py
lendres/data/BivariateAnalysis.py
lendres/data/DataComparison.py
lendres/data/DataHelper.py
lendres/data/DataHelperBase.py
lendres/data/UnivariateAnalysis.py
lendres/data/__init__.py
lendres/datatypes/ListTools.py
lendres/datatypes/__init__.py
lendres/demonstration/FunctionGenerator.py
lendres/demonstration/__init__.py
lendres/io/ConsoleHelper.py
lendres/io/IO.py
lendres/io/__init__.py
lendres/mathematics/Angles.py
lendres/mathematics/CoordinateTransform2d.py
lendres/mathematics/Precision.py
lendres/mathematics/__init__.py
lendres/modeling/LanguageHelper.py
lendres/modeling/__init__.py
lendres/path/File.py
lendres/path/Path.py
lendres/path/__init__.py
lendres/plotting/AnnotationHelper.py
lendres/plotting/AxesHelper.py
lendres/plotting/ColorHelper.py
lendres/plotting/FormatSettings.py
lendres/plotting/LegendHelper.py
lendres/plotting/LegendOptions.py
lendres/plotting/PlotHelper.py
lendres/plotting/PlotMaker.py
lendres/plotting/__init__.py
lendres/plotting/artistic.mplstyle
lendres/plotting/default.mplstyle
lendres/plotting/gridless.mplstyle
lendres/plotting/imagedefault.mplstyle
lendres/plotting/lightweightlines.mplstyle
lendres/plotting/manim.mplstyle
lendres/plotting/mediumsizefont.mplstyle
lendres/plotting/seaborn.mplstyle
lendres/plotting/transparentlegend.mplstyle
lendres/signalprocessing/SignalProcessing.py
lendres/utilities/PrintExecutable.py
lendres/utilities/__init__.py
lendres-0.2.0.dist-info/licenses/License.txt
lendres-0.2.0.dist-info/METADATA
lendres-0.2.0.dist-info/WHEEL
lendres-0.2.0.dist-info/top_level.txt
lendres-0.2.0.dist-info/RECORD
