Metadata-Version: 2.4
Name: lendres
Version: 0.2.0
Summary: A collection of general Python utilities from Lance A. Endres.
License: Copyright (c) 2021-2024 Lance A. Endres
Project-URL: homepage, https://github.com/lendres/Python
Requires-Python: >=3.11.0
License-File: License.txt
Requires-Dist: adjustText==1.2.0
Requires-Dist: beautifulsoup4==4.12.3
Requires-Dist: contractions==0.1.73
Requires-Dist: ipython==8.12.3
Requires-Dist: matplotlib==3.9.0
Requires-Dist: nltk==3.8.1
Requires-Dist: numpy==1.26.4
Requires-Dist: pandas==2.2.2
Requires-Dist: Pillow==10.4.0
Requires-Dist: scikit_learn==1.5.1
Requires-Dist: scipy==1.13.1
Requires-Dist: seaborn==0.13.2
Requires-Dist: spacy==3.7.5
Requires-Dist: wordcloud==1.9.3
Dynamic: license-file
